ai/__init__.py
ai/cs.py
ai/cxform-c.so
ai.cs-1.0.7.dist-info/DESCRIPTION.rst
ai.cs-1.0.7.dist-info/METADATA
ai.cs-1.0.7.dist-info/RECORD
ai.cs-1.0.7.dist-info/WHEEL
ai.cs-1.0.7.dist-info/metadata.json
ai.cs-1.0.7.dist-info/top_level.txt
