Metadata-Version: 1.1
Name: ai.cs
Version: 1.0.7
Summary: Coordinates transformation package for geocentric, heliocentric and geometrical coordinates
Home-page: https://bitbucket.org/isavnin/ai.cs
Author: Alexey Isavnin
Author-email: alexey.isavnin@gmail.com
License: MIT
Keywords: coordinates transformation cxform heliocentric geocentric
Platform: UNKNOWN
Classifier: Development Status :: 5 - Production/Stable
Classifier: Environment :: Console
Classifier: Intended Audience :: Science/Research
Classifier: License :: OSI Approved :: MIT License
Classifier: Programming Language :: Python :: 3
